{
	"id": 16410,
	"name": "tax-models",
	"variant": "project",
	"kind": 1,
	"flags": {},
	"comment": {
		"summary": [
			{
				"text": "## Relations Overview\n\n",
				"kind": "text"
			},
			{
				"text": "```mermaid\nerDiagram\n\tTaxRate ||--|| TaxRateRule : rules\n\tTaxRegion ||--|| TaxRegion : children\n\tTaxRegion ||--|| TaxRate : tax_rates\n\tTaxProvider ||--|| TaxRegion : regions\n\n```",
				"kind": "code"
			}
		]
	},
	"children": [
		{
			"id": 16533,
			"name": "TaxProvider",
			"variant": "declaration",
			"kind": 32,
			"flags": {
				"isConst": true
			},
			"sources": [
				{
					"fileName": "tax-provider.ts",
					"line": 4,
					"character": 6,
					"url": "https://github.com/medusajs/medusa/blob/fc377a136006df0f1c3d5cb6e0be340a486a03f0/packages/modules/tax/src/models/tax-provider.ts#L4"
				}
			],
			"type": {
				"type": "reference",
				"target": {
					"sourceFileName": "../../../../packages/core/utils/src/dml/entity.ts",
					"qualifiedName": "DmlEntity"
				},
				"typeArguments": [
					{
						"type": "reference",
						"target": {
							"sourceFileName": "../../../../packages/core/utils/src/dml/entity.ts",
							"qualifiedName": "DMLEntitySchemaBuilder"
						},
						"typeArguments": [
							{
								"type": "reflection",
								"declaration": {
									"id": 16534,
									"name": "__type",
									"variant": "declaration",
									"kind": 65536,
									"flags": {},
									"children": [
										{
											"id": 16535,
											"name": "id",
											"variant": "declaration",
											"kind": 1024,
											"flags": {},
											"comment": {
												"summary": [
													{
														"kind": "text",
														"text": "The ID of the tax provider."
													}
												]
											},
											"sources": [
												{
													"fileName": "tax-provider.ts",
													"line": 5,
													"character": 2,
													"url": "https://github.com/medusajs/medusa/blob/fc377a136006df0f1c3d5cb6e0be340a486a03f0/packages/modules/tax/src/models/tax-provider.ts#L5"
												}
											],
											"type": {
												"type": "reference",
												"target": {
													"sourceFileName": "../../../../packages/core/utils/src/dml/properties/primary-key.ts",
													"qualifiedName": "PrimaryKeyModifier"
												},
												"typeArguments": [
													{
														"type": "reference",
														"target": {
															"sourceFileName": "../../../../packages/core/utils/src/dml/properties/id.ts",
															"qualifiedName": "IdProperty"
														},
														"name": "IdProperty",
														"package": "@medusajs/utils"
													}
												],
												"name": "PrimaryKeyModifier",
												"package": "@medusajs/utils"
											},
											"defaultValue": "..."
										},
										{
											"id": 16536,
											"name": "is_enabled",
											"variant": "declaration",
											"kind": 1024,
											"flags": {},
											"comment": {
												"summary": [
													{
														"kind": "text",
														"text": "Whether the tax provider is enabled."
													}
												]
											},
											"sources": [
												{
													"fileName": "tax-provider.ts",
													"line": 6,
													"character": 2,
													"url": "https://github.com/medusajs/medusa/blob/fc377a136006df0f1c3d5cb6e0be340a486a03f0/packages/modules/tax/src/models/tax-provider.ts#L6"
												}
											],
											"type": {
												"type": "reference",
												"target": {
													"sourceFileName": "../../../../packages/core/utils/src/dml/properties/boolean.ts",
													"qualifiedName": "BooleanProperty"
												},
												"name": "BooleanProperty",
												"package": "@medusajs/utils"
											},
											"defaultValue": "..."
										},
										{
											"id": 16537,
											"name": "regions",
											"variant": "declaration",
											"kind": 1024,
											"flags": {},
											"comment": {
												"summary": [
													{
														"kind": "text",
														"text": "The regions that use this provider to calculate taxes."
													}
												],
												"modifierTags": [
													"@expandable"
												]
											},
											"sources": [
												{
													"fileName": "tax-provider.ts",
													"line": 7,
													"character": 2,
													"url": "https://github.com/medusajs/medusa/blob/fc377a136006df0f1c3d5cb6e0be340a486a03f0/packages/modules/tax/src/models/tax-provider.ts#L7"
												}
											],
											"type": {
												"type": "reference",
												"target": {
													"sourceFileName": "../../../../packages/core/utils/src/dml/relations/has-many.ts",
													"qualifiedName": "HasMany"
												},
												"typeArguments": [
													{
														"type": "reference",
														"target": 16458,
														"name": "TaxRegion"
													}
												],
												"name": "HasMany",
												"package": "@medusajs/utils"
											},
											"defaultValue": "..."
										}
									],
									"groups": [
										{
											"title": "Properties",
											"children": [
												16535,
												16536,
												16537
											]
										}
									],
									"sources": [
										{
											"fileName": "tax-provider.ts",
											"line": 4,
											"character": 48,
											"url": "https://github.com/medusajs/medusa/blob/fc377a136006df0f1c3d5cb6e0be340a486a03f0/packages/modules/tax/src/models/tax-provider.ts#L4"
										}
									]
								}
							}
						],
						"name": "DMLEntitySchemaBuilder",
						"package": "@medusajs/utils"
					},
					{
						"type": "literal",
						"value": "TaxProvider"
					}
				],
				"name": "DmlEntity",
				"package": "@medusajs/utils"
			},
			"defaultValue": "..."
		},
		{
			"id": 16508,
			"name": "TaxRateRule",
			"variant": "declaration",
			"kind": 32,
			"flags": {
				"isConst": true
			},
			"sources": [
				{
					"fileName": "tax-rate-rule.ts",
					"line": 4,
					"character": 6,
					"url": "https://github.com/medusajs/medusa/blob/fc377a136006df0f1c3d5cb6e0be340a486a03f0/packages/modules/tax/src/models/tax-rate-rule.ts#L4"
				}
			],
			"type": {
				"type": "reference",
				"target": {
					"sourceFileName": "../../../../packages/core/utils/src/dml/entity.ts",
					"qualifiedName": "DmlEntity"
				},
				"typeArguments": [
					{
						"type": "reference",
						"target": {
							"sourceFileName": "../../../../packages/core/utils/src/dml/entity.ts",
							"qualifiedName": "DMLEntitySchemaBuilder"
						},
						"typeArguments": [
							{
								"type": "reflection",
								"declaration": {
									"id": 16509,
									"name": "__type",
									"variant": "declaration",
									"kind": 65536,
									"flags": {},
									"children": [
										{
											"id": 16510,
											"name": "id",
											"variant": "declaration",
											"kind": 1024,
											"flags": {},
											"comment": {
												"summary": [
													{
														"kind": "text",
														"text": "The ID of the tax rate rule."
													}
												]
											},
											"sources": [
												{
													"fileName": "tax-rate-rule.ts",
													"line": 6,
													"character": 4,
													"url": "https://github.com/medusajs/medusa/blob/fc377a136006df0f1c3d5cb6e0be340a486a03f0/packages/modules/tax/src/models/tax-rate-rule.ts#L6"
												}
											],
											"type": {
												"type": "reference",
												"target": {
													"sourceFileName": "../../../../packages/core/utils/src/dml/properties/primary-key.ts",
													"qualifiedName": "PrimaryKeyModifier"
												},
												"typeArguments": [
													{
														"type": "reference",
														"target": {
															"sourceFileName": "../../../../packages/core/utils/src/dml/properties/id.ts",
															"qualifiedName": "IdProperty"
														},
														"name": "IdProperty",
														"package": "@medusajs/utils"
													}
												],
												"name": "PrimaryKeyModifier",
												"package": "@medusajs/utils"
											},
											"defaultValue": "..."
										},
										{
											"id": 16511,
											"name": "metadata",
											"variant": "declaration",
											"kind": 1024,
											"flags": {
												"isOptional": true
											},
											"comment": {
												"summary": [
													{
														"kind": "text",
														"text": "Holds custom data in key-value pairs."
													}
												]
											},
											"sources": [
												{
													"fileName": "tax-rate-rule.ts",
													"line": 7,
													"character": 4,
													"url": "https://github.com/medusajs/medusa/blob/fc377a136006df0f1c3d5cb6e0be340a486a03f0/packages/modules/tax/src/models/tax-rate-rule.ts#L7"
												}
											],
											"type": {
												"type": "reference",
												"target": {
													"sourceFileName": "../../../../packages/core/utils/src/dml/properties/json.ts",
													"qualifiedName": "JSONProperty"
												},
												"name": "JSONProperty",
												"package": "@medusajs/utils"
											},
											"defaultValue": "..."
										},
										{
											"id": 16512,
											"name": "created_by",
											"variant": "declaration",
											"kind": 1024,
											"flags": {
												"isOptional": true
											},
											"comment": {
												"summary": [
													{
														"kind": "text",
														"text": "The ID of the user that created the tax rate rule"
													}
												]
											},
											"sources": [
												{
													"fileName": "tax-rate-rule.ts",
													"line": 8,
													"character": 4,
													"url": "https://github.com/medusajs/medusa/blob/fc377a136006df0f1c3d5cb6e0be340a486a03f0/packages/modules/tax/src/models/tax-rate-rule.ts#L8"
												}
											],
											"type": {
												"type": "reference",
												"target": {
													"sourceFileName": "../../../../packages/core/utils/src/dml/properties/text.ts",
													"qualifiedName": "TextProperty"
												},
												"name": "TextProperty",
												"package": "@medusajs/utils"
											},
											"defaultValue": "..."
										},
										{
											"id": 16513,
											"name": "tax_rate",
											"variant": "declaration",
											"kind": 1024,
											"flags": {},
											"comment": {
												"summary": [
													{
														"kind": "text",
														"text": "The associated tax rate."
													}
												],
												"modifierTags": [
													"@expandable"
												]
											},
											"sources": [
												{
													"fileName": "tax-rate-rule.ts",
													"line": 9,
													"character": 4,
													"url": "https://github.com/medusajs/medusa/blob/fc377a136006df0f1c3d5cb6e0be340a486a03f0/packages/modules/tax/src/models/tax-rate-rule.ts#L9"
												}
											],
											"type": {
												"type": "reference",
												"target": {
													"sourceFileName": "../../../../packages/core/utils/src/dml/relations/belongs-to.ts",
													"qualifiedName": "BelongsTo"
												},
												"typeArguments": [
													{
														"type": "reference",
														"target": 16411,
														"name": "TaxRate"
													}
												],
												"name": "BelongsTo",
												"package": "@medusajs/utils"
											},
											"defaultValue": "..."
										},
										{
											"id": 16531,
											"name": "reference",
											"variant": "declaration",
											"kind": 1024,
											"flags": {},
											"comment": {
												"summary": [
													{
														"kind": "text",
														"text": "The name of the table this rule references.\n\n@example product_type"
													}
												]
											},
											"sources": [
												{
													"fileName": "tax-rate-rule.ts",
													"line": 12,
													"character": 4,
													"url": "https://github.com/medusajs/medusa/blob/fc377a136006df0f1c3d5cb6e0be340a486a03f0/packages/modules/tax/src/models/tax-rate-rule.ts#L12"
												}
											],
											"type": {
												"type": "reference",
												"target": {
													"sourceFileName": "../../../../packages/core/utils/src/dml/properties/text.ts",
													"qualifiedName": "TextProperty"
												},
												"name": "TextProperty",
												"package": "@medusajs/utils"
											},
											"defaultValue": "..."
										},
										{
											"id": 16532,
											"name": "reference_id",
											"variant": "declaration",
											"kind": 1024,
											"flags": {},
											"comment": {
												"summary": [
													{
														"kind": "text",
														"text": "The id of a record in the table that this rule references.\n\n@example ptyp_1"
													}
												]
											},
											"sources": [
												{
													"fileName": "tax-rate-rule.ts",
													"line": 13,
													"character": 4,
													"url": "https://github.com/medusajs/medusa/blob/fc377a136006df0f1c3d5cb6e0be340a486a03f0/packages/modules/tax/src/models/tax-rate-rule.ts#L13"
												}
											],
											"type": {
												"type": "reference",
												"target": {
													"sourceFileName": "../../../../packages/core/utils/src/dml/properties/text.ts",
													"qualifiedName": "TextProperty"
												},
												"name": "TextProperty",
												"package": "@medusajs/utils"
											},
											"defaultValue": "..."
										}
									],
									"groups": [
										{
											"title": "Properties",
											"children": [
												16510,
												16511,
												16512,
												16513,
												16531,
												16532
											]
										}
									],
									"sources": [
										{
											"fileName": "tax-rate-rule.ts",
											"line": 5,
											"character": 25,
											"url": "https://github.com/medusajs/medusa/blob/fc377a136006df0f1c3d5cb6e0be340a486a03f0/packages/modules/tax/src/models/tax-rate-rule.ts#L5"
										}
									]
								}
							}
						],
						"name": "DMLEntitySchemaBuilder",
						"package": "@medusajs/utils"
					},
					{
						"type": "literal",
						"value": "TaxRateRule"
					}
				],
				"name": "DmlEntity",
				"package": "@medusajs/utils"
			},
			"defaultValue": "..."
		},
		{
			"id": 16411,
			"name": "TaxRate",
			"variant": "declaration",
			"kind": 32,
			"flags": {
				"isConst": true
			},
			"sources": [
				{
					"fileName": "tax-rate.ts",
					"line": 5,
					"character": 6,
					"url": "https://github.com/medusajs/medusa/blob/fc377a136006df0f1c3d5cb6e0be340a486a03f0/packages/modules/tax/src/models/tax-rate.ts#L5"
				}
			],
			"type": {
				"type": "reference",
				"target": {
					"sourceFileName": "../../../../packages/core/utils/src/dml/entity.ts",
					"qualifiedName": "DmlEntity"
				},
				"typeArguments": [
					{
						"type": "reference",
						"target": {
							"sourceFileName": "../../../../packages/core/utils/src/dml/entity.ts",
							"qualifiedName": "DMLEntitySchemaBuilder"
						},
						"typeArguments": [
							{
								"type": "reflection",
								"declaration": {
									"id": 16412,
									"name": "__type",
									"variant": "declaration",
									"kind": 65536,
									"flags": {},
									"children": [
										{
											"id": 16413,
											"name": "id",
											"variant": "declaration",
											"kind": 1024,
											"flags": {},
											"comment": {
												"summary": [
													{
														"kind": "text",
														"text": "The ID of the tax rate."
													}
												]
											},
											"sources": [
												{
													"fileName": "tax-rate.ts",
													"line": 7,
													"character": 4,
													"url": "https://github.com/medusajs/medusa/blob/fc377a136006df0f1c3d5cb6e0be340a486a03f0/packages/modules/tax/src/models/tax-rate.ts#L7"
												}
											],
											"type": {
												"type": "reference",
												"target": {
													"sourceFileName": "../../../../packages/core/utils/src/dml/properties/primary-key.ts",
													"qualifiedName": "PrimaryKeyModifier"
												},
												"typeArguments": [
													{
														"type": "reference",
														"target": {
															"sourceFileName": "../../../../packages/core/utils/src/dml/properties/id.ts",
															"qualifiedName": "IdProperty"
														},
														"name": "IdProperty",
														"package": "@medusajs/utils"
													}
												],
												"name": "PrimaryKeyModifier",
												"package": "@medusajs/utils"
											},
											"defaultValue": "..."
										},
										{
											"id": 16414,
											"name": "rate",
											"variant": "declaration",
											"kind": 1024,
											"flags": {
												"isOptional": true
											},
											"comment": {
												"summary": [
													{
														"kind": "text",
														"text": "The rate to charge.\n\n@example 10"
													}
												]
											},
											"sources": [
												{
													"fileName": "tax-rate.ts",
													"line": 8,
													"character": 4,
													"url": "https://github.com/medusajs/medusa/blob/fc377a136006df0f1c3d5cb6e0be340a486a03f0/packages/modules/tax/src/models/tax-rate.ts#L8"
												}
											],
											"type": {
												"type": "reference",
												"target": {
													"sourceFileName": "../../../../packages/core/utils/src/dml/properties/float.ts",
													"qualifiedName": "FloatProperty"
												},
												"name": "FloatProperty",
												"package": "@medusajs/utils"
											},
											"defaultValue": "..."
										},
										{
											"id": 16415,
											"name": "code",
											"variant": "declaration",
											"kind": 1024,
											"flags": {},
											"comment": {
												"summary": [
													{
														"kind": "text",
														"text": "The code the tax rate is identified by."
													}
												]
											},
											"sources": [
												{
													"fileName": "tax-rate.ts",
													"line": 9,
													"character": 4,
													"url": "https://github.com/medusajs/medusa/blob/fc377a136006df0f1c3d5cb6e0be340a486a03f0/packages/modules/tax/src/models/tax-rate.ts#L9"
												}
											],
											"type": {
												"type": "reference",
												"target": {
													"sourceFileName": "../../../../packages/core/utils/src/dml/properties/text.ts",
													"qualifiedName": "TextProperty"
												},
												"name": "TextProperty",
												"package": "@medusajs/utils"
											},
											"defaultValue": "..."
										},
										{
											"id": 16416,
											"name": "name",
											"variant": "declaration",
											"kind": 1024,
											"flags": {},
											"comment": {
												"summary": [
													{
														"kind": "text",
														"text": "The name of the tax rate"
													}
												]
											},
											"sources": [
												{
													"fileName": "tax-rate.ts",
													"line": 10,
													"character": 4,
													"url": "https://github.com/medusajs/medusa/blob/fc377a136006df0f1c3d5cb6e0be340a486a03f0/packages/modules/tax/src/models/tax-rate.ts#L10"
												}
											],
											"type": {
												"type": "reference",
												"target": {
													"sourceFileName": "../../../../packages/core/utils/src/dml/properties/text.ts",
													"qualifiedName": "TextProperty"
												},
												"name": "TextProperty",
												"package": "@medusajs/utils"
											},
											"defaultValue": "..."
										},
										{
											"id": 16417,
											"name": "is_default",
											"variant": "declaration",
											"kind": 1024,
											"flags": {},
											"comment": {
												"summary": [
													{
														"kind": "text",
														"text": "Whether this tax rate is the default in the tax region."
													}
												]
											},
											"sources": [
												{
													"fileName": "tax-rate.ts",
													"line": 11,
													"character": 4,
													"url": "https://github.com/medusajs/medusa/blob/fc377a136006df0f1c3d5cb6e0be340a486a03f0/packages/modules/tax/src/models/tax-rate.ts#L11"
												}
											],
											"type": {
												"type": "reference",
												"target": {
													"sourceFileName": "../../../../packages/core/utils/src/dml/properties/boolean.ts",
													"qualifiedName": "BooleanProperty"
												},
												"name": "BooleanProperty",
												"package": "@medusajs/utils"
											},
											"defaultValue": "..."
										},
										{
											"id": 16418,
											"name": "is_combinable",
											"variant": "declaration",
											"kind": 1024,
											"flags": {},
											"comment": {
												"summary": [
													{
														"kind": "text",
														"text": "Whether the tax rate should be combined with parent rates. Learn more in [this documentation](https://docs.medusajs.com/v2/resources/commerce-modules/tax/tax-rates-and-rules#combinable-tax-rates)."
													}
												]
											},
											"sources": [
												{
													"fileName": "tax-rate.ts",
													"line": 12,
													"character": 4,
													"url": "https://github.com/medusajs/medusa/blob/fc377a136006df0f1c3d5cb6e0be340a486a03f0/packages/modules/tax/src/models/tax-rate.ts#L12"
												}
											],
											"type": {
												"type": "reference",
												"target": {
													"sourceFileName": "../../../../packages/core/utils/src/dml/properties/boolean.ts",
													"qualifiedName": "BooleanProperty"
												},
												"name": "BooleanProperty",
												"package": "@medusajs/utils"
											},
											"defaultValue": "..."
										},
										{
											"id": 16419,
											"name": "tax_region",
											"variant": "declaration",
											"kind": 1024,
											"flags": {},
											"comment": {
												"summary": [
													{
														"kind": "text",
														"text": "The associated tax region."
													}
												],
												"modifierTags": [
													"@expandable"
												]
											},
											"sources": [
												{
													"fileName": "tax-rate.ts",
													"line": 13,
													"character": 4,
													"url": "https://github.com/medusajs/medusa/blob/fc377a136006df0f1c3d5cb6e0be340a486a03f0/packages/modules/tax/src/models/tax-rate.ts#L13"
												}
											],
											"type": {
												"type": "reference",
												"target": {
													"sourceFileName": "../../../../packages/core/utils/src/dml/relations/belongs-to.ts",
													"qualifiedName": "BelongsTo"
												},
												"typeArguments": [
													{
														"type": "reference",
														"target": 16458,
														"name": "TaxRegion"
													}
												],
												"name": "BelongsTo",
												"package": "@medusajs/utils"
											},
											"defaultValue": "..."
										},
										{
											"id": 16444,
											"name": "rules",
											"variant": "declaration",
											"kind": 1024,
											"flags": {},
											"comment": {
												"summary": [
													{
														"kind": "text",
														"text": "The associated rules."
													}
												],
												"modifierTags": [
													"@expandable"
												]
											},
											"sources": [
												{
													"fileName": "tax-rate.ts",
													"line": 16,
													"character": 4,
													"url": "https://github.com/medusajs/medusa/blob/fc377a136006df0f1c3d5cb6e0be340a486a03f0/packages/modules/tax/src/models/tax-rate.ts#L16"
												}
											],
											"type": {
												"type": "reference",
												"target": {
													"sourceFileName": "../../../../packages/core/utils/src/dml/relations/has-many.ts",
													"qualifiedName": "HasMany"
												},
												"typeArguments": [
													{
														"type": "reference",
														"target": 16508,
														"name": "TaxRateRule"
													}
												],
												"name": "HasMany",
												"package": "@medusajs/utils"
											},
											"defaultValue": "..."
										},
										{
											"id": 16456,
											"name": "metadata",
											"variant": "declaration",
											"kind": 1024,
											"flags": {
												"isOptional": true
											},
											"comment": {
												"summary": [
													{
														"kind": "text",
														"text": "Holds custom data in key-value pairs."
													}
												]
											},
											"sources": [
												{
													"fileName": "tax-rate.ts",
													"line": 19,
													"character": 4,
													"url": "https://github.com/medusajs/medusa/blob/fc377a136006df0f1c3d5cb6e0be340a486a03f0/packages/modules/tax/src/models/tax-rate.ts#L19"
												}
											],
											"type": {
												"type": "reference",
												"target": {
													"sourceFileName": "../../../../packages/core/utils/src/dml/properties/json.ts",
													"qualifiedName": "JSONProperty"
												},
												"name": "JSONProperty",
												"package": "@medusajs/utils"
											},
											"defaultValue": "..."
										},
										{
											"id": 16457,
											"name": "created_by",
											"variant": "declaration",
											"kind": 1024,
											"flags": {
												"isOptional": true
											},
											"comment": {
												"summary": [
													{
														"kind": "text",
														"text": "The ID of the user that created the tax rate"
													}
												]
											},
											"sources": [
												{
													"fileName": "tax-rate.ts",
													"line": 20,
													"character": 4,
													"url": "https://github.com/medusajs/medusa/blob/fc377a136006df0f1c3d5cb6e0be340a486a03f0/packages/modules/tax/src/models/tax-rate.ts#L20"
												}
											],
											"type": {
												"type": "reference",
												"target": {
													"sourceFileName": "../../../../packages/core/utils/src/dml/properties/text.ts",
													"qualifiedName": "TextProperty"
												},
												"name": "TextProperty",
												"package": "@medusajs/utils"
											},
											"defaultValue": "..."
										}
									],
									"groups": [
										{
											"title": "Properties",
											"children": [
												16413,
												16414,
												16415,
												16416,
												16417,
												16418,
												16419,
												16444,
												16456,
												16457
											]
										}
									],
									"sources": [
										{
											"fileName": "tax-rate.ts",
											"line": 6,
											"character": 21,
											"url": "https://github.com/medusajs/medusa/blob/fc377a136006df0f1c3d5cb6e0be340a486a03f0/packages/modules/tax/src/models/tax-rate.ts#L6"
										}
									]
								}
							}
						],
						"name": "DMLEntitySchemaBuilder",
						"package": "@medusajs/utils"
					},
					{
						"type": "literal",
						"value": "TaxRate"
					}
				],
				"name": "DmlEntity",
				"package": "@medusajs/utils"
			},
			"defaultValue": "..."
		},
		{
			"id": 16458,
			"name": "TaxRegion",
			"variant": "declaration",
			"kind": 32,
			"flags": {
				"isConst": true
			},
			"sources": [
				{
					"fileName": "tax-region.ts",
					"line": 10,
					"character": 6,
					"url": "https://github.com/medusajs/medusa/blob/fc377a136006df0f1c3d5cb6e0be340a486a03f0/packages/modules/tax/src/models/tax-region.ts#L10"
				}
			],
			"type": {
				"type": "reference",
				"target": {
					"sourceFileName": "../../../../packages/core/utils/src/dml/entity.ts",
					"qualifiedName": "DmlEntity"
				},
				"typeArguments": [
					{
						"type": "reference",
						"target": {
							"sourceFileName": "../../../../packages/core/utils/src/dml/entity.ts",
							"qualifiedName": "DMLEntitySchemaBuilder"
						},
						"typeArguments": [
							{
								"type": "reflection",
								"declaration": {
									"id": 16459,
									"name": "__type",
									"variant": "declaration",
									"kind": 65536,
									"flags": {},
									"children": [
										{
											"id": 16460,
											"name": "id",
											"variant": "declaration",
											"kind": 1024,
											"flags": {},
											"comment": {
												"summary": [
													{
														"kind": "text",
														"text": "The ID of the tax region."
													}
												]
											},
											"sources": [
												{
													"fileName": "tax-region.ts",
													"line": 12,
													"character": 4,
													"url": "https://github.com/medusajs/medusa/blob/fc377a136006df0f1c3d5cb6e0be340a486a03f0/packages/modules/tax/src/models/tax-region.ts#L12"
												}
											],
											"type": {
												"type": "reference",
												"target": {
													"sourceFileName": "../../../../packages/core/utils/src/dml/properties/primary-key.ts",
													"qualifiedName": "PrimaryKeyModifier"
												},
												"typeArguments": [
													{
														"type": "reference",
														"target": {
															"sourceFileName": "../../../../packages/core/utils/src/dml/properties/id.ts",
															"qualifiedName": "IdProperty"
														},
														"name": "IdProperty",
														"package": "@medusajs/utils"
													}
												],
												"name": "PrimaryKeyModifier",
												"package": "@medusajs/utils"
											},
											"defaultValue": "..."
										},
										{
											"id": 16461,
											"name": "country_code",
											"variant": "declaration",
											"kind": 1024,
											"flags": {},
											"comment": {
												"summary": [
													{
														"kind": "text",
														"text": "The country code of the tax region.\n\n@example us"
													}
												]
											},
											"sources": [
												{
													"fileName": "tax-region.ts",
													"line": 13,
													"character": 4,
													"url": "https://github.com/medusajs/medusa/blob/fc377a136006df0f1c3d5cb6e0be340a486a03f0/packages/modules/tax/src/models/tax-region.ts#L13"
												}
											],
											"type": {
												"type": "reference",
												"target": {
													"sourceFileName": "../../../../packages/core/utils/src/dml/properties/text.ts",
													"qualifiedName": "TextProperty"
												},
												"name": "TextProperty",
												"package": "@medusajs/utils"
											},
											"defaultValue": "..."
										},
										{
											"id": 16462,
											"name": "province_code",
											"variant": "declaration",
											"kind": 1024,
											"flags": {
												"isOptional": true
											},
											"comment": {
												"summary": [
													{
														"kind": "text",
														"text": "The province code of the tax region"
													}
												]
											},
											"sources": [
												{
													"fileName": "tax-region.ts",
													"line": 14,
													"character": 4,
													"url": "https://github.com/medusajs/medusa/blob/fc377a136006df0f1c3d5cb6e0be340a486a03f0/packages/modules/tax/src/models/tax-region.ts#L14"
												}
											],
											"type": {
												"type": "reference",
												"target": {
													"sourceFileName": "../../../../packages/core/utils/src/dml/properties/text.ts",
													"qualifiedName": "TextProperty"
												},
												"name": "TextProperty",
												"package": "@medusajs/utils"
											},
											"defaultValue": "..."
										},
										{
											"id": 16463,
											"name": "metadata",
											"variant": "declaration",
											"kind": 1024,
											"flags": {
												"isOptional": true
											},
											"comment": {
												"summary": [
													{
														"kind": "text",
														"text": "Holds custom data in key-value pairs."
													}
												]
											},
											"sources": [
												{
													"fileName": "tax-region.ts",
													"line": 15,
													"character": 4,
													"url": "https://github.com/medusajs/medusa/blob/fc377a136006df0f1c3d5cb6e0be340a486a03f0/packages/modules/tax/src/models/tax-region.ts#L15"
												}
											],
											"type": {
												"type": "reference",
												"target": {
													"sourceFileName": "../../../../packages/core/utils/src/dml/properties/json.ts",
													"qualifiedName": "JSONProperty"
												},
												"name": "JSONProperty",
												"package": "@medusajs/utils"
											},
											"defaultValue": "..."
										},
										{
											"id": 16464,
											"name": "created_by",
											"variant": "declaration",
											"kind": 1024,
											"flags": {
												"isOptional": true
											},
											"comment": {
												"summary": [
													{
														"kind": "text",
														"text": "The ID of the user that created the tax region"
													}
												]
											},
											"sources": [
												{
													"fileName": "tax-region.ts",
													"line": 16,
													"character": 4,
													"url": "https://github.com/medusajs/medusa/blob/fc377a136006df0f1c3d5cb6e0be340a486a03f0/packages/modules/tax/src/models/tax-region.ts#L16"
												}
											],
											"type": {
												"type": "reference",
												"target": {
													"sourceFileName": "../../../../packages/core/utils/src/dml/properties/text.ts",
													"qualifiedName": "TextProperty"
												},
												"name": "TextProperty",
												"package": "@medusajs/utils"
											},
											"defaultValue": "..."
										},
										{
											"id": 16465,
											"name": "provider",
											"variant": "declaration",
											"kind": 1024,
											"flags": {
												"isOptional": true
											},
											"comment": {
												"summary": [
													{
														"kind": "text",
														"text": "The provider that calculates taxes in this region."
													}
												],
												"modifierTags": [
													"@expandable"
												]
											},
											"sources": [
												{
													"fileName": "tax-region.ts",
													"line": 17,
													"character": 4,
													"url": "https://github.com/medusajs/medusa/blob/fc377a136006df0f1c3d5cb6e0be340a486a03f0/packages/modules/tax/src/models/tax-region.ts#L17"
												}
											],
											"type": {
												"type": "reference",
												"target": {
													"sourceFileName": "../../../../packages/core/utils/src/dml/relations/belongs-to.ts",
													"qualifiedName": "BelongsTo"
												},
												"typeArguments": [
													{
														"type": "reference",
														"target": 16533,
														"name": "TaxProvider"
													}
												],
												"name": "BelongsTo",
												"package": "@medusajs/utils"
											},
											"defaultValue": "..."
										},
										{
											"id": 16482,
											"name": "parent",
											"variant": "declaration",
											"kind": 1024,
											"flags": {
												"isOptional": true
											},
											"comment": {
												"summary": [
													{
														"kind": "text",
														"text": "The tax region's parent."
													}
												],
												"modifierTags": [
													"@expandable"
												]
											},
											"sources": [
												{
													"fileName": "tax-region.ts",
													"line": 22,
													"character": 4,
													"url": "https://github.com/medusajs/medusa/blob/fc377a136006df0f1c3d5cb6e0be340a486a03f0/packages/modules/tax/src/models/tax-region.ts#L22"
												}
											],
											"type": {
												"type": "reference",
												"target": {
													"sourceFileName": "../../../../packages/core/utils/src/dml/relations/belongs-to.ts",
													"qualifiedName": "BelongsTo"
												},
												"typeArguments": [
													{
														"type": "reference",
														"target": 16458,
														"name": "TaxRegion"
													}
												],
												"name": "BelongsTo",
												"package": "@medusajs/utils"
											},
											"defaultValue": "..."
										},
										{
											"id": 16487,
											"name": "children",
											"variant": "declaration",
											"kind": 1024,
											"flags": {},
											"comment": {
												"summary": [
													{
														"kind": "text",
														"text": "The tax region's children.."
													}
												],
												"modifierTags": [
													"@expandable"
												]
											},
											"sources": [
												{
													"fileName": "tax-region.ts",
													"line": 27,
													"character": 4,
													"url": "https://github.com/medusajs/medusa/blob/fc377a136006df0f1c3d5cb6e0be340a486a03f0/packages/modules/tax/src/models/tax-region.ts#L27"
												}
											],
											"type": {
												"type": "reference",
												"target": {
													"sourceFileName": "../../../../packages/core/utils/src/dml/relations/has-many.ts",
													"qualifiedName": "HasMany"
												},
												"typeArguments": [
													{
														"type": "reference",
														"target": 16458,
														"name": "TaxRegion"
													}
												],
												"name": "HasMany",
												"package": "@medusajs/utils"
											},
											"defaultValue": "..."
										},
										{
											"id": 16490,
											"name": "tax_rates",
											"variant": "declaration",
											"kind": 1024,
											"flags": {},
											"comment": {
												"summary": [
													{
														"kind": "text",
														"text": "The associated tax rates."
													}
												],
												"modifierTags": [
													"@expandable"
												]
											},
											"sources": [
												{
													"fileName": "tax-region.ts",
													"line": 30,
													"character": 4,
													"url": "https://github.com/medusajs/medusa/blob/fc377a136006df0f1c3d5cb6e0be340a486a03f0/packages/modules/tax/src/models/tax-region.ts#L30"
												}
											],
											"type": {
												"type": "reference",
												"target": {
													"sourceFileName": "../../../../packages/core/utils/src/dml/relations/has-many.ts",
													"qualifiedName": "HasMany"
												},
												"typeArguments": [
													{
														"type": "reference",
														"target": 16411,
														"name": "TaxRate"
													}
												],
												"name": "HasMany",
												"package": "@medusajs/utils"
											},
											"defaultValue": "..."
										}
									],
									"groups": [
										{
											"title": "Properties",
											"children": [
												16460,
												16461,
												16462,
												16463,
												16464,
												16465,
												16482,
												16487,
												16490
											]
										}
									],
									"sources": [
										{
											"fileName": "tax-region.ts",
											"line": 11,
											"character": 23,
											"url": "https://github.com/medusajs/medusa/blob/fc377a136006df0f1c3d5cb6e0be340a486a03f0/packages/modules/tax/src/models/tax-region.ts#L11"
										}
									]
								}
							}
						],
						"name": "DMLEntitySchemaBuilder",
						"package": "@medusajs/utils"
					},
					{
						"type": "literal",
						"value": "TaxRegion"
					}
				],
				"name": "DmlEntity",
				"package": "@medusajs/utils"
			},
			"defaultValue": "..."
		}
	],
	"groups": [
		{
			"title": "Variables",
			"children": [
				16533,
				16508,
				16411,
				16458
			]
		}
	],
	"packageName": "@medusajs/tax",
	"symbolIdMap": {
		"16410": {
			"sourceFileName": "../../../../packages/modules/tax/src/models/index.ts",
			"qualifiedName": ""
		},
		"16411": {
			"sourceFileName": "../../../../packages/modules/tax/src/models/tax-rate.ts",
			"qualifiedName": "TaxRate"
		},
		"16412": {
			"sourceFileName": "../../../../packages/modules/tax/src/models/tax-rate.ts",
			"qualifiedName": "__object"
		},
		"16413": {
			"sourceFileName": "../../../../packages/modules/tax/src/models/tax-rate.ts",
			"qualifiedName": "__object.id"
		},
		"16414": {
			"sourceFileName": "../../../../packages/modules/tax/src/models/tax-rate.ts",
			"qualifiedName": "__object.rate"
		},
		"16415": {
			"sourceFileName": "../../../../packages/modules/tax/src/models/tax-rate.ts",
			"qualifiedName": "__object.code"
		},
		"16416": {
			"sourceFileName": "../../../../packages/modules/tax/src/models/tax-rate.ts",
			"qualifiedName": "__object.name"
		},
		"16417": {
			"sourceFileName": "../../../../packages/modules/tax/src/models/tax-rate.ts",
			"qualifiedName": "__object.is_default"
		},
		"16418": {
			"sourceFileName": "../../../../packages/modules/tax/src/models/tax-rate.ts",
			"qualifiedName": "__object.is_combinable"
		},
		"16419": {
			"sourceFileName": "../../../../packages/modules/tax/src/models/tax-rate.ts",
			"qualifiedName": "__object.tax_region"
		},
		"16420": {
			"sourceFileName": "../../../../packages/modules/tax/src/models/tax-rate.ts",
			"qualifiedName": "__function"
		},
		"16421": {
			"sourceFileName": "../../../../packages/modules/tax/src/models/tax-rate.ts",
			"qualifiedName": "__function"
		},
		"16422": {
			"sourceFileName": "../../../../packages/modules/tax/src/models/tax-region.ts",
			"qualifiedName": "__object"
		},
		"16423": {
			"sourceFileName": "../../../../packages/modules/tax/src/models/tax-region.ts",
			"qualifiedName": "__object.id"
		},
		"16424": {
			"sourceFileName": "../../../../packages/modules/tax/src/models/tax-region.ts",
			"qualifiedName": "__object.country_code"
		},
		"16425": {
			"sourceFileName": "../../../../packages/modules/tax/src/models/tax-region.ts",
			"qualifiedName": "__object.province_code"
		},
		"16426": {
			"sourceFileName": "../../../../packages/modules/tax/src/models/tax-region.ts",
			"qualifiedName": "__object.metadata"
		},
		"16427": {
			"sourceFileName": "../../../../packages/modules/tax/src/models/tax-region.ts",
			"qualifiedName": "__object.created_by"
		},
		"16428": {
			"sourceFileName": "../../../../packages/modules/tax/src/models/tax-region.ts",
			"qualifiedName": "__object.provider"
		},
		"16429": {
			"sourceFileName": "../../../../packages/modules/tax/src/models/tax-region.ts",
			"qualifiedName": "__function"
		},
		"16430": {
			"sourceFileName": "../../../../packages/modules/tax/src/models/tax-region.ts",
			"qualifiedName": "__function"
		},
		"16431": {
			"sourceFileName": "../../../../packages/modules/tax/src/models/tax-region.ts",
			"qualifiedName": "__function"
		},
		"16432": {
			"sourceFileName": "../../../../packages/modules/tax/src/models/tax-region.ts",
			"qualifiedName": "__function"
		},
		"16433": {
			"sourceFileName": "../../../../packages/modules/tax/src/models/tax-region.ts",
			"qualifiedName": "__object.parent"
		},
		"16434": {
			"sourceFileName": "../../../../packages/modules/tax/src/models/tax-region.ts",
			"qualifiedName": "__function"
		},
		"16435": {
			"sourceFileName": "../../../../packages/modules/tax/src/models/tax-region.ts",
			"qualifiedName": "__function"
		},
		"16436": {
			"sourceFileName": "../../../../packages/modules/tax/src/models/tax-region.ts",
			"qualifiedName": "__function"
		},
		"16437": {
			"sourceFileName": "../../../../packages/modules/tax/src/models/tax-region.ts",
			"qualifiedName": "__function"
		},
		"16438": {
			"sourceFileName": "../../../../packages/modules/tax/src/models/tax-region.ts",
			"qualifiedName": "__object.children"
		},
		"16439": {
			"sourceFileName": "../../../../packages/modules/tax/src/models/tax-region.ts",
			"qualifiedName": "__function"
		},
		"16440": {
			"sourceFileName": "../../../../packages/modules/tax/src/models/tax-region.ts",
			"qualifiedName": "__function"
		},
		"16441": {
			"sourceFileName": "../../../../packages/modules/tax/src/models/tax-region.ts",
			"qualifiedName": "__object.tax_rates"
		},
		"16442": {
			"sourceFileName": "../../../../packages/modules/tax/src/models/tax-region.ts",
			"qualifiedName": "__function"
		},
		"16443": {
			"sourceFileName": "../../../../packages/modules/tax/src/models/tax-region.ts",
			"qualifiedName": "__function"
		},
		"16444": {
			"sourceFileName": "../../../../packages/modules/tax/src/models/tax-rate.ts",
			"qualifiedName": "__object.rules"
		},
		"16445": {
			"sourceFileName": "../../../../packages/modules/tax/src/models/tax-rate.ts",
			"qualifiedName": "__function"
		},
		"16446": {
			"sourceFileName": "../../../../packages/modules/tax/src/models/tax-rate.ts",
			"qualifiedName": "__function"
		},
		"16447": {
			"sourceFileName": "../../../../packages/modules/tax/src/models/tax-rate-rule.ts",
			"qualifiedName": "__object"
		},
		"16448": {
			"sourceFileName": "../../../../packages/modules/tax/src/models/tax-rate-rule.ts",
			"qualifiedName": "__object.id"
		},
		"16449": {
			"sourceFileName": "../../../../packages/modules/tax/src/models/tax-rate-rule.ts",
			"qualifiedName": "__object.metadata"
		},
		"16450": {
			"sourceFileName": "../../../../packages/modules/tax/src/models/tax-rate-rule.ts",
			"qualifiedName": "__object.created_by"
		},
		"16451": {
			"sourceFileName": "../../../../packages/modules/tax/src/models/tax-rate-rule.ts",
			"qualifiedName": "__object.tax_rate"
		},
		"16452": {
			"sourceFileName": "../../../../packages/modules/tax/src/models/tax-rate-rule.ts",
			"qualifiedName": "__function"
		},
		"16453": {
			"sourceFileName": "../../../../packages/modules/tax/src/models/tax-rate-rule.ts",
			"qualifiedName": "__function"
		},
		"16454": {
			"sourceFileName": "../../../../packages/modules/tax/src/models/tax-rate-rule.ts",
			"qualifiedName": "__object.reference"
		},
		"16455": {
			"sourceFileName": "../../../../packages/modules/tax/src/models/tax-rate-rule.ts",
			"qualifiedName": "__object.reference_id"
		},
		"16456": {
			"sourceFileName": "../../../../packages/modules/tax/src/models/tax-rate.ts",
			"qualifiedName": "__object.metadata"
		},
		"16457": {
			"sourceFileName": "../../../../packages/modules/tax/src/models/tax-rate.ts",
			"qualifiedName": "__object.created_by"
		},
		"16458": {
			"sourceFileName": "../../../../packages/modules/tax/src/models/tax-region.ts",
			"qualifiedName": "TaxRegion"
		},
		"16459": {
			"sourceFileName": "../../../../packages/modules/tax/src/models/tax-region.ts",
			"qualifiedName": "__object"
		},
		"16460": {
			"sourceFileName": "../../../../packages/modules/tax/src/models/tax-region.ts",
			"qualifiedName": "__object.id"
		},
		"16461": {
			"sourceFileName": "../../../../packages/modules/tax/src/models/tax-region.ts",
			"qualifiedName": "__object.country_code"
		},
		"16462": {
			"sourceFileName": "../../../../packages/modules/tax/src/models/tax-region.ts",
			"qualifiedName": "__object.province_code"
		},
		"16463": {
			"sourceFileName": "../../../../packages/modules/tax/src/models/tax-region.ts",
			"qualifiedName": "__object.metadata"
		},
		"16464": {
			"sourceFileName": "../../../../packages/modules/tax/src/models/tax-region.ts",
			"qualifiedName": "__object.created_by"
		},
		"16465": {
			"sourceFileName": "../../../../packages/modules/tax/src/models/tax-region.ts",
			"qualifiedName": "__object.provider"
		},
		"16466": {
			"sourceFileName": "../../../../packages/modules/tax/src/models/tax-region.ts",
			"qualifiedName": "__function"
		},
		"16467": {
			"sourceFileName": "../../../../packages/modules/tax/src/models/tax-region.ts",
			"qualifiedName": "__function"
		},
		"16468": {
			"sourceFileName": "../../../../packages/modules/tax/src/models/tax-provider.ts",
			"qualifiedName": "__object"
		},
		"16469": {
			"sourceFileName": "../../../../packages/modules/tax/src/models/tax-provider.ts",
			"qualifiedName": "__object.id"
		},
		"16470": {
			"sourceFileName": "../../../../packages/modules/tax/src/models/tax-provider.ts",
			"qualifiedName": "__object.is_enabled"
		},
		"16471": {
			"sourceFileName": "../../../../packages/modules/tax/src/models/tax-provider.ts",
			"qualifiedName": "__object.regions"
		},
		"16472": {
			"sourceFileName": "../../../../packages/modules/tax/src/models/tax-provider.ts",
			"qualifiedName": "__function"
		},
		"16473": {
			"sourceFileName": "../../../../packages/modules/tax/src/models/tax-provider.ts",
			"qualifiedName": "__function"
		},
		"16474": {
			"sourceFileName": "../../../../packages/modules/tax/src/models/tax-region.ts",
			"qualifiedName": "__function"
		},
		"16475": {
			"sourceFileName": "../../../../packages/modules/tax/src/models/tax-region.ts",
			"qualifiedName": "__function"
		},
		"16476": {
			"sourceFileName": "../../../../packages/modules/tax/src/models/tax-provider.ts",
			"qualifiedName": "__object"
		},
		"16477": {
			"sourceFileName": "../../../../packages/modules/tax/src/models/tax-provider.ts",
			"qualifiedName": "__object.id"
		},
		"16478": {
			"sourceFileName": "../../../../packages/modules/tax/src/models/tax-provider.ts",
			"qualifiedName": "__object.is_enabled"
		},
		"16479": {
			"sourceFileName": "../../../../packages/modules/tax/src/models/tax-provider.ts",
			"qualifiedName": "__object.regions"
		},
		"16480": {
			"sourceFileName": "../../../../packages/modules/tax/src/models/tax-provider.ts",
			"qualifiedName": "__function"
		},
		"16481": {
			"sourceFileName": "../../../../packages/modules/tax/src/models/tax-provider.ts",
			"qualifiedName": "__function"
		},
		"16482": {
			"sourceFileName": "../../../../packages/modules/tax/src/models/tax-region.ts",
			"qualifiedName": "__object.parent"
		},
		"16483": {
			"sourceFileName": "../../../../packages/modules/tax/src/models/tax-region.ts",
			"qualifiedName": "__function"
		},
		"16484": {
			"sourceFileName": "../../../../packages/modules/tax/src/models/tax-region.ts",
			"qualifiedName": "__function"
		},
		"16485": {
			"sourceFileName": "../../../../packages/modules/tax/src/models/tax-region.ts",
			"qualifiedName": "__function"
		},
		"16486": {
			"sourceFileName": "../../../../packages/modules/tax/src/models/tax-region.ts",
			"qualifiedName": "__function"
		},
		"16487": {
			"sourceFileName": "../../../../packages/modules/tax/src/models/tax-region.ts",
			"qualifiedName": "__object.children"
		},
		"16488": {
			"sourceFileName": "../../../../packages/modules/tax/src/models/tax-region.ts",
			"qualifiedName": "__function"
		},
		"16489": {
			"sourceFileName": "../../../../packages/modules/tax/src/models/tax-region.ts",
			"qualifiedName": "__function"
		},
		"16490": {
			"sourceFileName": "../../../../packages/modules/tax/src/models/tax-region.ts",
			"qualifiedName": "__object.tax_rates"
		},
		"16491": {
			"sourceFileName": "../../../../packages/modules/tax/src/models/tax-region.ts",
			"qualifiedName": "__function"
		},
		"16492": {
			"sourceFileName": "../../../../packages/modules/tax/src/models/tax-region.ts",
			"qualifiedName": "__function"
		},
		"16493": {
			"sourceFileName": "../../../../packages/modules/tax/src/models/tax-rate.ts",
			"qualifiedName": "__object"
		},
		"16494": {
			"sourceFileName": "../../../../packages/modules/tax/src/models/tax-rate.ts",
			"qualifiedName": "__object.id"
		},
		"16495": {
			"sourceFileName": "../../../../packages/modules/tax/src/models/tax-rate.ts",
			"qualifiedName": "__object.rate"
		},
		"16496": {
			"sourceFileName": "../../../../packages/modules/tax/src/models/tax-rate.ts",
			"qualifiedName": "__object.code"
		},
		"16497": {
			"sourceFileName": "../../../../packages/modules/tax/src/models/tax-rate.ts",
			"qualifiedName": "__object.name"
		},
		"16498": {
			"sourceFileName": "../../../../packages/modules/tax/src/models/tax-rate.ts",
			"qualifiedName": "__object.is_default"
		},
		"16499": {
			"sourceFileName": "../../../../packages/modules/tax/src/models/tax-rate.ts",
			"qualifiedName": "__object.is_combinable"
		},
		"16500": {
			"sourceFileName": "../../../../packages/modules/tax/src/models/tax-rate.ts",
			"qualifiedName": "__object.tax_region"
		},
		"16501": {
			"sourceFileName": "../../../../packages/modules/tax/src/models/tax-rate.ts",
			"qualifiedName": "__function"
		},
		"16502": {
			"sourceFileName": "../../../../packages/modules/tax/src/models/tax-rate.ts",
			"qualifiedName": "__function"
		},
		"16503": {
			"sourceFileName": "../../../../packages/modules/tax/src/models/tax-rate.ts",
			"qualifiedName": "__object.rules"
		},
		"16504": {
			"sourceFileName": "../../../../packages/modules/tax/src/models/tax-rate.ts",
			"qualifiedName": "__function"
		},
		"16505": {
			"sourceFileName": "../../../../packages/modules/tax/src/models/tax-rate.ts",
			"qualifiedName": "__function"
		},
		"16506": {
			"sourceFileName": "../../../../packages/modules/tax/src/models/tax-rate.ts",
			"qualifiedName": "__object.metadata"
		},
		"16507": {
			"sourceFileName": "../../../../packages/modules/tax/src/models/tax-rate.ts",
			"qualifiedName": "__object.created_by"
		},
		"16508": {
			"sourceFileName": "../../../../packages/modules/tax/src/models/tax-rate-rule.ts",
			"qualifiedName": "TaxRateRule"
		},
		"16509": {
			"sourceFileName": "../../../../packages/modules/tax/src/models/tax-rate-rule.ts",
			"qualifiedName": "__object"
		},
		"16510": {
			"sourceFileName": "../../../../packages/modules/tax/src/models/tax-rate-rule.ts",
			"qualifiedName": "__object.id"
		},
		"16511": {
			"sourceFileName": "../../../../packages/modules/tax/src/models/tax-rate-rule.ts",
			"qualifiedName": "__object.metadata"
		},
		"16512": {
			"sourceFileName": "../../../../packages/modules/tax/src/models/tax-rate-rule.ts",
			"qualifiedName": "__object.created_by"
		},
		"16513": {
			"sourceFileName": "../../../../packages/modules/tax/src/models/tax-rate-rule.ts",
			"qualifiedName": "__object.tax_rate"
		},
		"16514": {
			"sourceFileName": "../../../../packages/modules/tax/src/models/tax-rate-rule.ts",
			"qualifiedName": "__function"
		},
		"16515": {
			"sourceFileName": "../../../../packages/modules/tax/src/models/tax-rate-rule.ts",
			"qualifiedName": "__function"
		},
		"16516": {
			"sourceFileName": "../../../../packages/modules/tax/src/models/tax-rate.ts",
			"qualifiedName": "__object"
		},
		"16517": {
			"sourceFileName": "../../../../packages/modules/tax/src/models/tax-rate.ts",
			"qualifiedName": "__object.id"
		},
		"16518": {
			"sourceFileName": "../../../../packages/modules/tax/src/models/tax-rate.ts",
			"qualifiedName": "__object.rate"
		},
		"16519": {
			"sourceFileName": "../../../../packages/modules/tax/src/models/tax-rate.ts",
			"qualifiedName": "__object.code"
		},
		"16520": {
			"sourceFileName": "../../../../packages/modules/tax/src/models/tax-rate.ts",
			"qualifiedName": "__object.name"
		},
		"16521": {
			"sourceFileName": "../../../../packages/modules/tax/src/models/tax-rate.ts",
			"qualifiedName": "__object.is_default"
		},
		"16522": {
			"sourceFileName": "../../../../packages/modules/tax/src/models/tax-rate.ts",
			"qualifiedName": "__object.is_combinable"
		},
		"16523": {
			"sourceFileName": "../../../../packages/modules/tax/src/models/tax-rate.ts",
			"qualifiedName": "__object.tax_region"
		},
		"16524": {
			"sourceFileName": "../../../../packages/modules/tax/src/models/tax-rate.ts",
			"qualifiedName": "__function"
		},
		"16525": {
			"sourceFileName": "../../../../packages/modules/tax/src/models/tax-rate.ts",
			"qualifiedName": "__function"
		},
		"16526": {
			"sourceFileName": "../../../../packages/modules/tax/src/models/tax-rate.ts",
			"qualifiedName": "__object.rules"
		},
		"16527": {
			"sourceFileName": "../../../../packages/modules/tax/src/models/tax-rate.ts",
			"qualifiedName": "__function"
		},
		"16528": {
			"sourceFileName": "../../../../packages/modules/tax/src/models/tax-rate.ts",
			"qualifiedName": "__function"
		},
		"16529": {
			"sourceFileName": "../../../../packages/modules/tax/src/models/tax-rate.ts",
			"qualifiedName": "__object.metadata"
		},
		"16530": {
			"sourceFileName": "../../../../packages/modules/tax/src/models/tax-rate.ts",
			"qualifiedName": "__object.created_by"
		},
		"16531": {
			"sourceFileName": "../../../../packages/modules/tax/src/models/tax-rate-rule.ts",
			"qualifiedName": "__object.reference"
		},
		"16532": {
			"sourceFileName": "../../../../packages/modules/tax/src/models/tax-rate-rule.ts",
			"qualifiedName": "__object.reference_id"
		},
		"16533": {
			"sourceFileName": "../../../../packages/modules/tax/src/models/tax-provider.ts",
			"qualifiedName": "TaxProvider"
		},
		"16534": {
			"sourceFileName": "../../../../packages/modules/tax/src/models/tax-provider.ts",
			"qualifiedName": "__object"
		},
		"16535": {
			"sourceFileName": "../../../../packages/modules/tax/src/models/tax-provider.ts",
			"qualifiedName": "__object.id"
		},
		"16536": {
			"sourceFileName": "../../../../packages/modules/tax/src/models/tax-provider.ts",
			"qualifiedName": "__object.is_enabled"
		},
		"16537": {
			"sourceFileName": "../../../../packages/modules/tax/src/models/tax-provider.ts",
			"qualifiedName": "__object.regions"
		},
		"16538": {
			"sourceFileName": "../../../../packages/modules/tax/src/models/tax-provider.ts",
			"qualifiedName": "__function"
		},
		"16539": {
			"sourceFileName": "../../../../packages/modules/tax/src/models/tax-provider.ts",
			"qualifiedName": "__function"
		},
		"16540": {
			"sourceFileName": "../../../../packages/modules/tax/src/models/tax-region.ts",
			"qualifiedName": "__object"
		},
		"16541": {
			"sourceFileName": "../../../../packages/modules/tax/src/models/tax-region.ts",
			"qualifiedName": "__object.id"
		},
		"16542": {
			"sourceFileName": "../../../../packages/modules/tax/src/models/tax-region.ts",
			"qualifiedName": "__object.country_code"
		},
		"16543": {
			"sourceFileName": "../../../../packages/modules/tax/src/models/tax-region.ts",
			"qualifiedName": "__object.province_code"
		},
		"16544": {
			"sourceFileName": "../../../../packages/modules/tax/src/models/tax-region.ts",
			"qualifiedName": "__object.metadata"
		},
		"16545": {
			"sourceFileName": "../../../../packages/modules/tax/src/models/tax-region.ts",
			"qualifiedName": "__object.created_by"
		},
		"16546": {
			"sourceFileName": "../../../../packages/modules/tax/src/models/tax-region.ts",
			"qualifiedName": "__object.provider"
		},
		"16547": {
			"sourceFileName": "../../../../packages/modules/tax/src/models/tax-region.ts",
			"qualifiedName": "__function"
		},
		"16548": {
			"sourceFileName": "../../../../packages/modules/tax/src/models/tax-region.ts",
			"qualifiedName": "__function"
		},
		"16549": {
			"sourceFileName": "../../../../packages/modules/tax/src/models/tax-region.ts",
			"qualifiedName": "__function"
		},
		"16550": {
			"sourceFileName": "../../../../packages/modules/tax/src/models/tax-region.ts",
			"qualifiedName": "__function"
		},
		"16551": {
			"sourceFileName": "../../../../packages/modules/tax/src/models/tax-region.ts",
			"qualifiedName": "__object.parent"
		},
		"16552": {
			"sourceFileName": "../../../../packages/modules/tax/src/models/tax-region.ts",
			"qualifiedName": "__function"
		},
		"16553": {
			"sourceFileName": "../../../../packages/modules/tax/src/models/tax-region.ts",
			"qualifiedName": "__function"
		},
		"16554": {
			"sourceFileName": "../../../../packages/modules/tax/src/models/tax-region.ts",
			"qualifiedName": "__function"
		},
		"16555": {
			"sourceFileName": "../../../../packages/modules/tax/src/models/tax-region.ts",
			"qualifiedName": "__function"
		},
		"16556": {
			"sourceFileName": "../../../../packages/modules/tax/src/models/tax-region.ts",
			"qualifiedName": "__object.children"
		},
		"16557": {
			"sourceFileName": "../../../../packages/modules/tax/src/models/tax-region.ts",
			"qualifiedName": "__function"
		},
		"16558": {
			"sourceFileName": "../../../../packages/modules/tax/src/models/tax-region.ts",
			"qualifiedName": "__function"
		},
		"16559": {
			"sourceFileName": "../../../../packages/modules/tax/src/models/tax-region.ts",
			"qualifiedName": "__object.tax_rates"
		},
		"16560": {
			"sourceFileName": "../../../../packages/modules/tax/src/models/tax-region.ts",
			"qualifiedName": "__function"
		},
		"16561": {
			"sourceFileName": "../../../../packages/modules/tax/src/models/tax-region.ts",
			"qualifiedName": "__function"
		}
	},
	"files": {
		"entries": {
			"1": "../../../../packages/modules/tax/src/models/index.ts"
		},
		"reflections": {
			"1": 16410
		}
	}
}
